{"action_sequence_name": "Tolerance_Measurement_SWASI_Paper", "action_log": [{"0_Create Assembly Instruction": {"service_client": "/assembly_manager/create_assembly_instruction_from_description", "service_type": "assembly_manager_interfaces/srv/CreateAssemblyInstructionFromDescription", "srv_start_time": "2024-02-12_21:01:42.071566", "srv_end_time": "2024-02-12_21:01:44.757209", "execution_time": "0:00:02.685643", "srv_request": {"file_path": "/home/niklas/Documents/SolidWorks_ASsembly_Instructor/examples/SWASI_Paper_Demonstrator_V2/SWASI_Exports/assemblies/Baugruppe_S17_MODTOL.json", "spawn_components": true}, "srv_response": {"instruction_id": "Description_Glas_Platelet_Paper-1_UFC_Paper-2", "success": true}, "success": true}}, {"1_Calculate Assembly Instruction": {"service_client": "/assembly_manager/calculate_assembly_instructions", "service_type": "assembly_manager_interfaces/srv/CalculateAssemblyInstructions", "srv_start_time": "2024-02-12_21:01:44.759611", "srv_end_time": "2024-02-12_21:01:47.244223", "execution_time": "0:00:02.484612", "srv_request": {"instruction_id": "Description_Glas_Platelet_Paper-1_UFC_Paper-2"}, "srv_response": {"success": true, "assembly_transform": {"position": {"x": 0.800947191722946, "y": -1.1754264157004535e-06, "z": 0.4819991964914423}, "orientation": {"x": -0.0002717167420603157, "y": 1.5639878168949617e-05, "z": 2.0628399457881936e-05, "w": 0.999999962749937}}}, "success": true}}, {"2_Get Scene": {"service_client": "/assembly_manager/get_scene", "service_type": "assembly_manager_interfaces/srv/GetScene", "srv_start_time": "2024-02-12_21:01:47.245948", "srv_end_time": "2024-02-12_21:01:47.249727", "execution_time": "0:00:00.003779", "srv_request": {}, "srv_response": {"scene": {"objects_in_scene": [{"obj_name": "UFC_Paper_MODTOL-2", "parent_frame": "Test_Station", "obj_pose": {"position": {"x": 0.0, "y": 0.0, "z": 0.02}, "orientation": {"x": 0.0, "y": 0.0, "z": 0.0, "w": 1.0}}, "cad_data": "/home/niklas/Documents/SolidWorks_ASsembly_Instructor/examples/SWASI_Paper_Demonstrator_V2/SWASI_Exports/components/UFC_Paper.STL", "ref_frames": [{"frame_name": "UFC_Paper_MODTOL-2_Vision_Point_1", "parent_frame": "UFC_Paper_MODTOL-2", "pose": {"position": {"x": -0.0013704652957757025, "y": -0.002465297398634764, "z": 0.0020009655189981664}, "orientation": {"x": 0.0, "y": 0.0, "z": 0.0, "w": 1.0}}, "constraints_dict": "{'constraints': {'units': 'mm'}}"}, {"frame_name": "UFC_Paper_MODTOL-2_Vision_Point_1_helper", "parent_frame": "UFC_Paper_MODTOL-2", "pose": {"position": {"x": -0.0013704927238291798, "y": -0.0024656446691148815, "z": -7.345596382331959e-07}, "orientation": {"x": 0.0, "y": 0.0, "z": 0.0, "w": 1.0}}, "constraints_dict": "{'constraints': {'units': 'mm'}}"}, {"frame_name": "UFC_Paper_MODTOL-2_Vision_Point_2", "parent_frame": "UFC_Paper_MODTOL-2", "pose": {"position": {"x": -0.0017706674175329488, "y": -0.02000104801881916, "z": 0.0020006113777653544}, "orientation": {"x": 0.0, "y": 0.0, "z": 0.0, "w": 1.0}}, "constraints_dict": "{'constraints': {'units': 'mm'}}"}, {"frame_name": "UFC_Paper_MODTOL-2_Vision_Point_2_helper", "parent_frame": "UFC_Paper_MODTOL-2", "pose": {"position": {"x": -0.0017712345709263854, "y": -0.019999521044330858, "z": 1.3539924036986344e-06}, "orientation": {"x": 0.0, "y": 0.0, "z": 0.0, "w": 1.0}}, "constraints_dict": "{'constraints': {'units': 'mm'}}"}, {"frame_name": "UFC_Paper_MODTOL-2_Vision_Point_3", "parent_frame": "UFC_Paper_MODTOL-2", "pose": {"position": {"x": -0.02999853748788863, "y": -0.020000738491236597, "z": 0.00200072705533995}, "orientation": {"x": 0.0, "y": 0.0, "z": 0.0, "w": 1.0}}, "constraints_dict": "{'constraints': {'units': 'mm'}}"}, {"frame_name": "UFC_Paper_MODTOL-2_Vision_Point_3_helper", "parent_frame": "UFC_Paper_MODTOL-2", "pose": {"position": {"x": -0.029999717521847356, "y": -0.02000055981684894, "z": -5.403633582762684e-07}, "orientation": {"x": 0.0, "y": 0.0, "z": 0.0, "w": 1.0}}, "constraints_dict": "{'constraints': {'units': 'mm'}}"}, {"frame_name": "UFC_Paper_MODTOL-2_Vision_Point_4", "parent_frame": "UFC_Paper_MODTOL-2", "pose": {"position": {"x": -0.030341851037104434, "y": -0.0003811922862561962, "z": 0.0020013667558233775}, "orientation": {"x": 0.0, "y": 0.0, "z": 0.0, "w": 1.0}}, "constraints_dict": "{'constraints': {'units': 'mm'}}"}, {"frame_name": "UFC_Paper_MODTOL-2_Surface_Center_Point", "parent_frame": "UFC_Paper_MODTOL-2", "pose": {"position": {"x": -0.01588547604638687, "y": -0.0200000404305899, "z": 4.06814522711183e-07}, "orientation": {"x": 0.0, "y": 0.0, "z": 0.0, "w": 1.0}}, "constraints_dict": "{'constraints': {'centroid': {'ref_frame_names': ['Vision_Point_2_helper', 'Vision_Point_3_helper'], 'dim': 'xyz', 'offset_values': [0, 0, 0]}, 'units': 'mm'}}"}, {"frame_name": "UFC_Paper_MODTOL-2_Gripping_Point", "parent_frame": "UFC_Paper_MODTOL-2", "pose": {"position": {"x": -0.01587038030957543, "y": -0.010712069048736679, "z": 0.002000917676981712}, "orientation": {"x": 0.0, "y": 0.0, "z": 0.0, "w": 1.0}}, "constraints_dict": "{'constraints': {'centroid': {'ref_frame_names': ['Vision_Point_1', 'Vision_Point_2', 'Vision_Point_3', 'Vision_Point_4'], 'dim': 'xyz', 'offset_values': [0, 0, 0]}, 'units': 'mm'}}"}, {"frame_name": "UFC_Paper_MODTOL-2_Laser_Mes_Frame_1", "parent_frame": "UFC_Paper_MODTOL-2", "pose": {"position": {"x": -0.00185573387, "y": -0.00223329163, "z": 0.002}, "orientation": {"x": 0.0, "y": 0.0, "z": 0.0, "w": 1.0}}, "constraints_dict": "{'constraints': {'units': 'mm'}}"}, {"frame_name": "UFC_Paper_MODTOL-2_Laser_Mes_Frame_2", "parent_frame": "UFC_Paper_MODTOL-2", "pose": {"position": {"x": -0.00185573387, "y": -0.0202332916, "z": 0.002}, "orientation": {"x": 0.0, "y": 0.0, "z": 0.0, "w": 1.0}}, "constraints_dict": "{'constraints': {'units': 'mm'}}"}, {"frame_name": "UFC_Paper_MODTOL-2_Laser_Mes_Frame_3", "parent_frame": "UFC_Paper_MODTOL-2", "pose": {"position": {"x": -0.029855732, "y": -0.0202332916, "z": 0.002}, "orientation": {"x": 0.0, "y": 0.0, "z": 0.0, "w": 1.0}}, "constraints_dict": "{'constraints': {'units': 'mm'}}"}, {"frame_name": "UFC_Paper_MODTOL-2_Laser_Mes_Frame_4", "parent_frame": "UFC_Paper_MODTOL-2", "pose": {"position": {"x": -0.029855732, "y": -0.00223329163, "z": 0.002}, "orientation": {"x": 0.0, "y": 0.0, "z": 0.0, "w": 1.0}}, "constraints_dict": "{'constraints': {'units': 'mm'}}"}, {"frame_name": "assembly_frame_Description_Glas_Platelet_Paper-1_UFC_Paper-2", "parent_frame": "UFC_Paper_MODTOL-2", "pose": {"position": {"x": -0.0158854760712459, "y": -0.019999365228975996, "z": 4.0691854086283286e-07}, "orientation": {"x": 0.0, "y": 0.0, "z": 1.0, "w": 0.0}}, "constraints_dict": "{}"}], "ref_axis": [{"axis_name": "UFC_Paper_MODTOL-2_Norm_Alignment_Plane_3", "point_names": ["UFC_Paper_MODTOL-2_Vision_Point_2_helper", "UFC_Paper_MODTOL-2_Vision_Point_3_helper"]}], "ref_planes": [{"ref_plane_name": "UFC_Paper_MODTOL-2_Alignment_Plane_1", "point_names": ["UFC_Paper_MODTOL-2_Vision_Point_2_helper", "UFC_Paper_MODTOL-2_Vision_Point_2", "UFC_Paper_MODTOL-2_Vision_Point_3"], "axis_names": [""], "ideal_norm_vector": {"x": -1.64540865e-17, "y": -1.0, "z": 6.519618e-30}}, {"ref_plane_name": "UFC_Paper_MODTOL-2_Alignment_Plane_2ddasd", "point_names": ["UFC_Paper_MODTOL-2_Vision_Point_3_helper", "UFC_Paper_MODTOL-2_Vision_Point_2_helper", "UFC_Paper_MODTOL-2_Vision_Point_1_helper"], "axis_names": [""], "ideal_norm_vector": {"x": 0.0, "y": 0.0, "z": 1.0}}, {"ref_plane_name": "UFC_Paper_MODTOL-2_Alignment_Plane_3", "point_names": ["UFC_Paper_MODTOL-2_Surface_Center_Point", "", ""], "axis_names": ["UFC_Paper_MODTOL-2_Norm_Alignment_Plane_3"], "ideal_norm_vector": {"x": -1.0, "y": 1.64540865e-17, "z": 0.0}}]}, {"obj_name": "Glas_Platelet_Paper_MODTOL-1", "parent_frame": "Test_Station", "obj_pose": {"position": {"x": 0.8, "y": 0.0, "z": 0.5}, "orientation": {"x": 0.0, "y": 0.0, "z": 0.0, "w": 1.0}}, "cad_data": "/home/niklas/Documents/SolidWorks_ASsembly_Instructor/examples/SWASI_Paper_Demonstrator_V2/SWASI_Exports/components/Glas_Platelet_Paper.STL", "ref_frames": [{"frame_name": "Glas_Platelet_Paper_MODTOL-1_Vision_Point_1", "parent_frame": "Glas_Platelet_Paper_MODTOL-1", "pose": {"position": {"x": 5.53664887287664e-05, "y": -0.00041895079560507197, "z": 0.0020008821850632627}, "orientation": {"x": 0.0, "y": 0.0, "z": 0.0, "w": 1.0}}, "constraints_dict": "{'constraints': {'units': 'mm'}}"}, {"frame_name": "Glas_Platelet_Paper_MODTOL-1_Vision_Point_1_helper", "parent_frame": "Glas_Platelet_Paper_MODTOL-1", "pose": {"position": {"x": 5.8019975711056636e-05, "y": -0.000417176528551523, "z": 3.578470000176063e-08}, "orientation": {"x": 0.0, "y": 0.0, "z": 0.0, "w": 1.0}}, "constraints_dict": "{'constraints': {'units': 'mm'}}"}, {"frame_name": "Glas_Platelet_Paper_MODTOL-1_Vision_Point_2", "parent_frame": "Glas_Platelet_Paper_MODTOL-1", "pose": {"position": {"x": 0.00012672349030315566, "y": -0.019999358596476627, "z": 0.0020002876942784974}, "orientation": {"x": 0.0, "y": 0.0, "z": 0.0, "w": 1.0}}, "constraints_dict": "{'constraints': {'units': 'mm'}}"}, {"frame_name": "Glas_Platelet_Paper_MODTOL-1_Vision_Point_2_helper", "parent_frame": "Glas_Platelet_Paper_MODTOL-1", "pose": {"position": {"x": 0.00012387285657391073, "y": -0.020000306919555767, "z": 1.8638215046543407e-06}, "orientation": {"x": 0.0, "y": 0.0, "z": 0.0, "w": 1.0}}, "constraints_dict": "{'constraints': {'units': 'mm'}}"}, {"frame_name": "Glas_Platelet_Paper_MODTOL-1_Vision_Point_3", "parent_frame": "Glas_Platelet_Paper_MODTOL-1", "pose": {"position": {"x": -0.02999933030035663, "y": -0.020001722024728746, "z": 0.0019989188848280365}, "orientation": {"x": 0.0, "y": 0.0, "z": 0.0, "w": 1.0}}, "constraints_dict": "{'constraints': {'units': 'mm'}}"}, {"frame_name": "Glas_Platelet_Paper_MODTOL-1_Vision_Point_3_helper", "parent_frame": "Glas_Platelet_Paper_MODTOL-1", "pose": {"position": {"x": -0.030000337004157933, "y": -0.02000120815929573, "z": 1.0761177577283885e-06}, "orientation": {"x": 0.0, "y": 0.0, "z": 0.0, "w": 1.0}}, "constraints_dict": "{'constraints': {'units': 'mm'}}"}, {"frame_name": "Glas_Platelet_Paper_MODTOL-1_Vision_Point_4", "parent_frame": "Glas_Platelet_Paper_MODTOL-1", "pose": {"position": {"x": -0.027700542862049083, "y": -0.00041815566078283494, "z": 0.0020007900093525865}, "orientation": {"x": 0.0, "y": 0.0, "z": 0.0, "w": 1.0}}, "constraints_dict": "{'constraints': {'units': 'mm'}}"}, {"frame_name": "Glas_Platelet_Paper_MODTOL-1_Surface_Center_Point", "parent_frame": "Glas_Platelet_Paper_MODTOL-1", "pose": {"position": {"x": -0.014938232073792012, "y": -0.020000757539425748, "z": 1.4699696311913646e-06}, "orientation": {"x": 0.0, "y": 0.0, "z": 0.0, "w": 1.0}}, "constraints_dict": "{'constraints': {'centroid': {'ref_frame_names': ['Vision_Point_2_helper', 'Vision_Point_3_helper'], 'dim': 'xyz', 'offset_values': [0, 0, 0]}, 'units': 'mm'}}"}, {"frame_name": "Glas_Platelet_Paper_MODTOL-1_Laser_Mes_Frame_1", "parent_frame": "Glas_Platelet_Paper_MODTOL-1", "pose": {"position": {"x": 0.000178403854, "y": -0.001208559, "z": 0.002}, "orientation": {"x": 0.0, "y": 0.0, "z": 0.0, "w": 1.0}}, "constraints_dict": "{'constraints': {'units': 'mm'}}"}, {"frame_name": "Glas_Platelet_Paper_MODTOL-1_Laser_Mes_Frame_2", "parent_frame": "Glas_Platelet_Paper_MODTOL-1", "pose": {"position": {"x": 0.000178403854, "y": -0.019208559, "z": 0.002}, "orientation": {"x": 0.0, "y": 0.0, "z": 0.0, "w": 1.0}}, "constraints_dict": "{'constraints': {'units': 'mm'}}"}, {"frame_name": "Glas_Platelet_Paper_MODTOL-1_Laser_Mes_Frame_3", "parent_frame": "Glas_Platelet_Paper_MODTOL-1", "pose": {"position": {"x": -0.027821596100000002, "y": -0.019208559, "z": 0.002}, "orientation": {"x": 0.0, "y": 0.0, "z": 0.0, "w": 1.0}}, "constraints_dict": "{'constraints': {'units': 'mm'}}"}, {"frame_name": "Glas_Platelet_Paper_MODTOL-1_Laser_Mes_Frame_4", "parent_frame": "Glas_Platelet_Paper_MODTOL-1", "pose": {"position": {"x": -0.027821596100000002, "y": -0.001208559, "z": 0.002}, "orientation": {"x": 0.0, "y": 0.0, "z": 0.0, "w": 1.0}}, "constraints_dict": "{'constraints': {'units': 'mm'}}"}, {"frame_name": "target_frame_Description_Glas_Platelet_Paper-1_UFC_Paper-2", "parent_frame": "Glas_Platelet_Paper_MODTOL-1", "pose": {"position": {"x": -0.014938284348299913, "y": -0.020000540655391696, "z": 0.001999603409982953}, "orientation": {"x": 1.5639878168949614e-05, "y": 2.0628399457881933e-05, "z": 0.9999999627499371, "w": -0.00027171674206031567}}, "constraints_dict": "{}"}], "ref_axis": [{"axis_name": "Glas_Platelet_Paper_MODTOL-1_Norm_Alignment_Plane_3", "point_names": ["Glas_Platelet_Paper_MODTOL-1_Vision_Point_2_helper", "Glas_Platelet_Paper_MODTOL-1_Vision_Point_3_helper"]}], "ref_planes": [{"ref_plane_name": "Glas_Platelet_Paper_MODTOL-1_Alignment_Plane_1", "point_names": ["Glas_Platelet_Paper_MODTOL-1_Vision_Point_2_helper", "Glas_Platelet_Paper_MODTOL-1_Vision_Point_2", "Glas_Platelet_Paper_MODTOL-1_Vision_Point_3"], "axis_names": [""], "ideal_norm_vector": {"x": -1.64540865e-17, "y": -1.0, "z": 6.519618e-30}}, {"ref_plane_name": "Glas_Platelet_Paper_MODTOL-1_Alignment_Plane_2", "point_names": ["Glas_Platelet_Paper_MODTOL-1_Vision_Point_2", "Glas_Platelet_Paper_MODTOL-1_Vision_Point_3", "Glas_Platelet_Paper_MODTOL-1_Vision_Point_1"], "axis_names": [""], "ideal_norm_vector": {"x": 0.0, "y": 0.0, "z": -1.0}}, {"ref_plane_name": "Glas_Platelet_Paper_MODTOL-1_Alignment_Plane_3_G", "point_names": ["Glas_Platelet_Paper_MODTOL-1_Surface_Center_Point", "", ""], "axis_names": ["Glas_Platelet_Paper_MODTOL-1_Norm_Alignment_Plane_3"], "ideal_norm_vector": {"x": -1.0, "y": 1.547762e-17, "z": 0.0}}]}], "ref_frames_in_scene": [], "axis_in_scene": [], "planes_in_scene": [], "assembly_instructions": [{"id": "Description_Glas_Platelet_Paper-1_UFC_Paper-2", "component_1_is_moving_part": false, "plane_match_1": {"plane_name_component_1": "Glas_Platelet_Paper_MODTOL-1_Alignment_Plane_1", "plane_name_component_2": "UFC_Paper_MODTOL-2_Alignment_Plane_1", "plane_offset": 0.0, "inv_normal_vector": false}, "plane_match_2": {"plane_name_component_1": "Glas_Platelet_Paper_MODTOL-1_Alignment_Plane_2", "plane_name_component_2": "UFC_Paper_MODTOL-2_Alignment_Plane_2ddasd", "plane_offset": 0.0, "inv_normal_vector": true}, "plane_match_3": {"plane_name_component_1": "Glas_Platelet_Paper_MODTOL-1_Alignment_Plane_3_G", "plane_name_component_2": "UFC_Paper_MODTOL-2_Alignment_Plane_3", "plane_offset": 0.0, "inv_normal_vector": false}}]}, "success": true}, "success": true}}]}