{"action_sequence_name": "Mount_IpeG_Demonstrator", "action_log": [{"17_/pm_moveit_server/move_cam1_to_frame": {"service_client": "/pm_moveit_server/move_cam1_to_frame", "service_type": "pm_moveit_interfaces/srv/MoveToFrame", "srv_start_time": "2024-02-22_01:20:28.720303", "srv_end_time": "2024-02-22_01:20:31.101509", "execution_time": "0:00:02.381206", "srv_request": {"endeffector_frame_override": "LB1092-1_Camera_Measurement_Point_1", "target_frame": "Camera_Station_TCP", "translation": {"x": 0.0, "y": 0.0, "z": 0.0}, "rotation": {"x": 0.0, "y": 0.0, "z": 0.0, "w": 1.0}, "execute_movement": true}, "srv_response": {"success": true, "joint_names": ["X_Axis_Joint", "Y_Axis_Joint", "Z_Axis_Joint"], "joint_values": [-0.36859315633773804, -0.01805562525987625, 0.008597435429692268], "message": ""}, "success": true}}]}